codebrick/__init__.py
codebrick/brick.py
codebrick/cli.py
codebrick/rich_console.py
codebrick/bricks/aiohttp_server.py
codebrick/bricks/aiohttp_ws_client.py
codebrick/bricks/fastapi_server.py
codebrick/bricks/flask.py
codebrick/bricks/helloworld.py
codebrick/bricks/rich_console.py
codebrick/bricks/ws_client.py
codebrick-1.0.2.dist-info/METADATA
codebrick-1.0.2.dist-info/WHEEL
codebrick-1.0.2.dist-info/entry_points.txt
codebrick-1.0.2.dist-info/top_level.txt
codebrick-1.0.2.dist-info/RECORD
